AUTHORS.txt
LICENSE.txt
MANIFEST.in
NEWS.txt
README.rst
setup.cfg
setup.py
./djangotestapp/__init__.py
./djangotestapp/manage.py
./djangotestapp/settings.py
./djangotestapp/urls.py
./spawning/__init__.py
./spawning/django_factory.py
./spawning/memory_watcher.py
./spawning/paste_factory.py
./spawning/reloader_dev.py
./spawning/reloader_svn.py
./spawning/spawning_child.py
./spawning/spawning_controller.py
./spawning/wsgi_factory.py
./spawning/util/__init__.py
./spawning/util/log_parser.py
./spawning/util/status.py
./spawning/util/system.py
Spawning.egg-info/PKG-INFO
Spawning.egg-info/SOURCES.txt
Spawning.egg-info/dependency_links.txt
Spawning.egg-info/entry_points.txt
Spawning.egg-info/requires.txt
Spawning.egg-info/top_level.txt
rc-scripts/conf.d/spawning
rc-scripts/init.d/spawning
rc-scripts/init.d/spawning.debian
rc-scripts/init.d/spawning.fedora
rc-scripts/sysconfig/spawning.fedora
spawning/__init__.py
spawning/django_factory.py
spawning/memory_watcher.py
spawning/paste_factory.py
spawning/reloader_dev.py
spawning/reloader_svn.py
spawning/spawning_child.py
spawning/spawning_controller.py
spawning/wsgi_factory.py
spawning/util/__init__.py
spawning/util/log_parser.py
spawning/util/status.py
spawning/util/system.py