Metadata-Version: 1.0
Name: Spawning
Version: 0.9.7
Summary: Spawning is a wsgi server which supports multiple processes, multiple threads, green threads, non-blocking HTTP io, and automatic graceful upgrading of code.
Home-page: UNKNOWN
Author: R. Tyler Croy
Author-email: tyler@monkeypox.org
License: UNKNOWN
Platform: UNKNOWN
Classifier: License :: OSI Approved :: MIT License
Classifier: Programming Language :: Python
Classifier: Operating System :: MacOS :: MacOS X
Classifier: Operating System :: POSIX
Classifier: Topic :: Internet
Classifier: Topic :: Software Development :: Libraries :: Python Modules
Classifier: Intended Audience :: Developers
Classifier: Development Status :: 4 - Beta
